pufo_twitter_bot/__init__.py
pufo_twitter_bot/__main__.py
pufo_twitter_bot/authors/__init__.py
pufo_twitter_bot/authors/opendatanames.py
pufo_twitter_bot/authors/randomnames.py
pufo_twitter_bot/books/__init__.py
pufo_twitter_bot/books/randombuch.py
pufo_twitter_bot/bot/__init__.py
pufo_twitter_bot/bot/twitter.py
pufo_twitter_bot/data/Vornamen_Koeln_2010.csv
pufo_twitter_bot/data/Vornamen_Koeln_2011.csv
pufo_twitter_bot/data/Vornamen_Koeln_2012.csv
pufo_twitter_bot/data/Vornamen_Koeln_2013.csv
pufo_twitter_bot/data/Vornamen_Koeln_2014.csv
pufo_twitter_bot/data/first-names-merged.csv
pufo_twitter_bot/data/first-names.json
pufo_twitter_bot/data/last-names.txt
pufo_twitter_bot/py.typed
pufo_twitter_bot-0.4.0.dist-info/LICENSE.rst
pufo_twitter_bot-0.4.0.dist-info/METADATA
pufo_twitter_bot-0.4.0.dist-info/WHEEL
pufo_twitter_bot-0.4.0.dist-info/entry_points.txt
pufo_twitter_bot-0.4.0.dist-info/RECORD
