Metadata-Version: 2.1
Name: pufo-twitter-bot
Version: 0.4.0
Summary: Pufo Twitter Bot
Home-page: https://github.com/mjt91/pufo-twitter-bot
License: MIT
Author: Marius Theiss
Author-email: justusbersten@gmail.com
Requires-Python: >=3.8,<4.0.0
Classifier: License :: OSI Approved :: MIT License
Classifier: Programming Language :: Python :: 3
Classifier: Programming Language :: Python :: 3.8
Classifier: Programming Language :: Python :: 3.9
Classifier: Programming Language :: Python :: 3.10
Classifier: Programming Language :: Python :: 3.11
Classifier: Programming Language :: Python :: 3.8
Classifier: Programming Language :: Python :: 3.9
Requires-Dist: beautifulsoup4 (>=4.9.3)
Requires-Dist: click (>=7.0)
Requires-Dist: desert (>=2020.11.18)
Requires-Dist: marshmallow (>=3.11.1)
Requires-Dist: requests (>=2.25.1)
Requires-Dist: tweepy (>=3.10.0)
Project-URL: Changelog, https://github.com/mjt91/pufo-twitter-bot/releases
Project-URL: Documentation, https://pufo-twitter-bot.readthedocs.io
Project-URL: Repository, https://github.com/mjt91/pufo-twitter-bot
